inputless_graph/__init__.py
inputless_graph/example_usage.py
inputless_graph/features/__init__.py
inputless_graph/features/natural_language_behavior_queries.py
inputless_graph/features/quantum_inspired_processing.py
inputless_graph/graph_models.py
inputless_graph/graph_queries.py
inputless_graph/graph_rag_engine.py
inputless_graph/insight_generator.py
inputless_graph/neo4j_repository.py
inputless_graph/nl_query_agent.py
inputless_graph-1.0.2.dist-info/METADATA
inputless_graph-1.0.2.dist-info/WHEEL
inputless_graph-1.0.2.dist-info/RECORD
