Metadata-Version: 2.4
Name: inputless-graph
Version: 1.0.2
Summary: Neo4j graph database integration, Graph RAG engine, and natural language query agent
Author: Inputless Team
Author-email: team@inputless.io
Requires-Python: >=3.11,<4.0
Classifier: Programming Language :: Python :: 3
Classifier: Programming Language :: Python :: 3.11
Classifier: Programming Language :: Python :: 3.12
Classifier: Programming Language :: Python :: 3.13
Classifier: Programming Language :: Python :: 3.14
Requires-Dist: anthropic (>=0.30.0,<0.31.0)
Requires-Dist: httpx (>=0.26.0,<0.27.0)
Requires-Dist: langchain (>=0.3.0,<0.4.0)
Requires-Dist: langchain-anthropic (>=0.2.0,<0.3.0)
Requires-Dist: langchain-openai (>=0.2.0,<0.3.0)
Requires-Dist: neo4j (>=5.15.0,<6.0.0)
Requires-Dist: networkx (>=3.2.1,<4.0.0)
Requires-Dist: openai (>=1.12.0,<2.0.0)
Requires-Dist: pydantic (>=2.5.3,<3.0.0)
